rcabench_platform/__init__.py
rcabench_platform/compat.py
rcabench_platform/py.typed
rcabench_platform/v2/algorithms/random_.py
rcabench_platform/v2/algorithms/rcaeval/_common.py
rcabench_platform/v2/algorithms/rcaeval/baro.py
rcabench_platform/v2/algorithms/rcaeval/nsigma.py
rcabench_platform/v2/algorithms/spec.py
rcabench_platform/v2/algorithms/traceback/A10.py
rcabench_platform/v2/algorithms/traceback/A7.py
rcabench_platform/v2/algorithms/traceback/A8.py
rcabench_platform/v2/algorithms/traceback/A9.py
rcabench_platform/v2/algorithms/traceback/_common.py
rcabench_platform/v2/algorithms/traceback/a10/bootstrap.py
rcabench_platform/v2/algorithms/traceback/a10/dataloader.py
rcabench_platform/v2/algorithms/traceback/a10/model.py
rcabench_platform/v2/algorithms/traceback/a10/refiner.py
rcabench_platform/v2/analysis/aggregation.py
rcabench_platform/v2/analysis/algo_perf_vis.py
rcabench_platform/v2/analysis/data_prepare.py
rcabench_platform/v2/analysis/datapacks_analysis.py
rcabench_platform/v2/analysis/datapacks_visualiaztion.py
rcabench_platform/v2/analysis/detector_visualization.py
rcabench_platform/v2/cli/container.py
rcabench_platform/v2/cli/eval.py
rcabench_platform/v2/cli/main.py
rcabench_platform/v2/cli/online.py
rcabench_platform/v2/cli/sample.py
rcabench_platform/v2/cli/sdg.py
rcabench_platform/v2/cli/self_.py
rcabench_platform/v2/cli/tools.py
rcabench_platform/v2/clients/clickhouse.py
rcabench_platform/v2/clients/k8s.py
rcabench_platform/v2/clients/neo4j.py
rcabench_platform/v2/clients/rcabench_.py
rcabench_platform/v2/cloud/hf.py
rcabench_platform/v2/cloud/minio_.py
rcabench_platform/v2/cloud/spec.py
rcabench_platform/v2/config.py
rcabench_platform/v2/datasets/rcabench.py
rcabench_platform/v2/datasets/rcaeval.py
rcabench_platform/v2/datasets/spec.py
rcabench_platform/v2/datasets/train_ticket.py
rcabench_platform/v2/evaluation/ranking.py
rcabench_platform/v2/experiments/batch.py
rcabench_platform/v2/experiments/report.py
rcabench_platform-0.4.1.dist-info/WHEEL
rcabench_platform-0.4.1.dist-info/entry_points.txt
rcabench_platform-0.4.1.dist-info/METADATA
rcabench_platform-0.4.1.dist-info/RECORD
